[{"code":"enabled","inputType":"text","label":"enabled"},{"code":"label","inputType":"text","label":"label"},{"code":"decal","inputType":"text","label":"decal"},{"inputType":"children","isArr":false,"title":"label","config":[{"code":"label.enabled","inputType":"text","label":"enabled","nextCode":"enabled"},{"code":"label.description","inputType":"text","label":"description","nextCode":"description"},{"code":"label.general","inputType":"text","label":"general","nextCode":"general"},{"code":"label.series","inputType":"text","label":"series","nextCode":"series"},{"code":"label.data","inputType":"text","label":"data","nextCode":"data"},{"inputType":"children","isArr":false,"title":"general","config":[{"code":"label.general.withTitle","inputType":"text","label":"withTitle","nextCode":"withTitle"},{"code":"label.general.withoutTitle","inputType":"text","label":"withoutTitle","nextCode":"withoutTitle"}]},{"inputType":"children","isArr":false,"title":"series","config":[{"code":"label.series.maxCount","inputType":"text","label":"maxCount","nextCode":"maxCount"},{"code":"label.series.single","inputType":"text","label":"single","nextCode":"single"},{"code":"label.series.multiple","inputType":"text","label":"multiple","nextCode":"multiple"},{"inputType":"children","isArr":false,"title":"single","config":[{"code":"label.series.single.prefix","inputType":"text","label":"prefix","nextCode":"prefix"},{"code":"label.series.single.withName","inputType":"text","label":"withName","nextCode":"withName"},{"code":"label.series.single.withoutName","inputType":"text","label":"withoutName","nextCode":"withoutName"}]},{"inputType":"children","isArr":false,"title":"multiple","config":[{"code":"label.series.multiple.prefix","inputType":"text","label":"prefix","nextCode":"prefix"},{"code":"label.series.multiple.withName","inputType":"text","label":"withName","nextCode":"withName"},{"code":"label.series.multiple.withoutName","inputType":"text","label":"withoutName","nextCode":"withoutName"},{"code":"label.series.multiple.separator","inputType":"text","label":"separator","nextCode":"separator"},{"inputType":"children","isArr":false,"title":"separator","config":[{"code":"label.series.multiple.separator.middle","inputType":"text","label":"middle","nextCode":"middle"},{"code":"label.series.multiple.separator.end","inputType":"text","label":"end","nextCode":"end"}]}]}]},{"inputType":"children","isArr":true,"title":"data","config":[{"code":"label.data.maxCount","inputType":"text","label":"maxCount","nextCode":"maxCount"},{"code":"label.data.allData","inputType":"text","label":"allData","nextCode":"allData"},{"code":"label.data.partialData","inputType":"text","label":"partialData","nextCode":"partialData"},{"code":"label.data.withName","inputType":"text","label":"withName","nextCode":"withName"},{"code":"label.data.withoutName","inputType":"text","label":"withoutName","nextCode":"withoutName"},{"code":"label.data.separator","inputType":"text","label":"separator","nextCode":"separator"},{"inputType":"children","isArr":false,"title":"separator","config":[{"code":"label.data.separator.middle","inputType":"text","label":"middle","nextCode":"middle"},{"code":"label.data.separator.end","inputType":"text","label":"end","nextCode":"end"}]}]}]},{"inputType":"children","isArr":false,"title":"decal","config":[{"code":"decal.show","inputType":"text","label":"show","nextCode":"show"},{"code":"decal.decals","inputType":"text","label":"decals","nextCode":"decals"},{"inputType":"children","isArr":false,"title":"decals","config":[{"code":"decal.decals.symbol","inputType":"text","label":"symbol","nextCode":"symbol"},{"code":"decal.decals.symbolSize","inputType":"text","label":"symbolSize","nextCode":"symbolSize"},{"code":"decal.decals.symbolKeepAspect","inputType":"text","label":"symbolKeepAspect","nextCode":"symbolKeepAspect"},{"code":"decal.decals.color","inputType":"text","label":"color","nextCode":"color"},{"code":"decal.decals.backgroundColor","inputType":"text","label":"backgroundColor","nextCode":"backgroundColor"},{"code":"decal.decals.dashArrayX","inputType":"text","label":"dashArrayX","nextCode":"dashArrayX"},{"code":"decal.decals.dashArrayY","inputType":"text","label":"dashArrayY","nextCode":"dashArrayY"},{"code":"decal.decals.rotation","inputType":"text","label":"rotation","nextCode":"rotation"},{"code":"decal.decals.maxTileWidth","inputType":"text","label":"maxTileWidth","nextCode":"maxTileWidth"},{"code":"decal.decals.maxTileHeight","inputType":"text","label":"maxTileHeight","nextCode":"maxTileHeight"}]}]}]